LICENSE
MANIFEST.in
README.rst
requirements.txt
setup.py
hotstar_m3u8.egg-info/PKG-INFO
hotstar_m3u8.egg-info/SOURCES.txt
hotstar_m3u8.egg-info/dependency_links.txt
hotstar_m3u8.egg-info/not-zip-safe
hotstar_m3u8.egg-info/requires.txt
hotstar_m3u8.egg-info/top_level.txt
m3u8/__init__.py
m3u8/mixins.py
m3u8/model.py
m3u8/parser.py
m3u8/protocol.py