Metadata-Version: 1.2
Name: hotstar-m3u8
Version: 0.5.5
Summary: Python m3u8 parser
Home-page: https://github.com/gsingh42/m3u8
Author: hotstar.com
Author-email: gaurav.s@hotstar.com
License: MIT
Platform: UNKNOWN
Requires-Python: >=2.7
